amapy_plugin_gcs/__init__.py
amapy_plugin_gcs/bucket_cors.py
amapy_plugin_gcs/gcs_blob.py
amapy_plugin_gcs/gcs_storage.py
amapy_plugin_gcs/gcs_storage_mixin.py
amapy_plugin_gcs/gcs_utils.py
amapy_plugin_gcs/signed_url.py
amapy_plugin_gcs/tests/__init__.py
amapy_plugin_gcs/tests/test_bucket_cors.py
amapy_plugin_gcs/tests/test_gcs_storage.py
amapy_plugin_gcs/transporter/__init__.py
amapy_plugin_gcs/transporter/gcs_transport_resource.py
amapy_plugin_gcs/transporter/async_gcs/__init__.py
amapy_plugin_gcs/transporter/async_gcs/async_copy.py
amapy_plugin_gcs/transporter/async_gcs/async_delete.py
amapy_plugin_gcs/transporter/async_gcs/async_download.py
amapy_plugin_gcs/transporter/async_gcs/async_gcs_transporter.py
amapy_plugin_gcs/transporter/async_gcs/async_storage.py
amapy_plugin_gcs/transporter/async_gcs/async_upload.py
amapy_plugin_gcs/transporter/async_gcs/tests/__init__.py
amapy_plugin_gcs/transporter/async_gcs/tests/test_async_gcs_transporter.py
amapy_plugin_gcs-1.0.1.dist-info/METADATA
amapy_plugin_gcs-1.0.1.dist-info/WHEEL
amapy_plugin_gcs-1.0.1.dist-info/top_level.txt
amapy_plugin_gcs-1.0.1.dist-info/RECORD
