Metadata-Version: 2.1
Name: amapy-plugin-gcs
Version: 1.0.1
Summary: The GCS plugin for the ama project.
Author-email: Swarup Mahanti <swarup.mahanti@roche.com>
Maintainer-email: Swarup Mahanti <swarup.mahanti@roche.com>
License: Copyright (c) 2024 Roche Diagnostics Computation Science & Informatics
Requires-Python: <3.11,>=3.10
Requires-Dist: amapy-contents==1.*
Requires-Dist: amapy-pluggy==1.*
Requires-Dist: amapy-utils==1.*
Requires-Dist: backoff==2.2.*
Requires-Dist: gcloud-aio-storage==9.3.*
Requires-Dist: google-cloud-storage==2.10.*
